plct_sphinx_components/__init__.py
plct_sphinx_components/extensions/__init__.py
plct_sphinx_components/extensions/database_queries/__init__.py
plct_sphinx_components/extensions/database_queries/css/database-queries.css
plct_sphinx_components/extensions/database_queries/database_queries.py
plct_sphinx_components/extensions/database_queries/js/database-queries.js
plct_sphinx_components/extensions/fill_in_the_blank/__init__.py
plct_sphinx_components/extensions/fill_in_the_blank/css/fill-in-the-blank.css
plct_sphinx_components/extensions/fill_in_the_blank/fill_in_the_blank.py
plct_sphinx_components/extensions/fill_in_the_blank/images/fitb-background.svg
plct_sphinx_components/extensions/fill_in_the_blank/js/fill-in-the-blank.js
plct_sphinx_components/extensions/multiple_choice/__init__.py
plct_sphinx_components/extensions/multiple_choice/css/multiple-choice.css
plct_sphinx_components/extensions/multiple_choice/images/choice-background.svg
plct_sphinx_components/extensions/multiple_choice/images/qchoice-img.svg
plct_sphinx_components/extensions/multiple_choice/js/multiple-choice.js
plct_sphinx_components/extensions/multiple_choice/multiple_choice.py
plct_sphinx_components/extensions/notes/__init__.py
plct_sphinx_components/extensions/notes/css/notes.css
plct_sphinx_components/extensions/notes/images/infonote-img.svg
plct_sphinx_components/extensions/notes/images/learnmorenote-img.svg
plct_sphinx_components/extensions/notes/images/question-mark.png
plct_sphinx_components/extensions/notes/images/questionnote-img.svg
plct_sphinx_components/extensions/notes/images/suggestionnote-img.svg
plct_sphinx_components/extensions/notes/images/technicalnote-img.svg
plct_sphinx_components/extensions/notes/js/notes.js
plct_sphinx_components/extensions/notes/notes.py
plct_sphinx_components/extensions/py_code/__init__.py
plct_sphinx_components/extensions/py_code/css/py-code.css
plct_sphinx_components/extensions/py_code/js/py-code.js
plct_sphinx_components/extensions/py_code/py_code.py
plct_sphinx_components-0.0.5.dist-info/LICENSE
plct_sphinx_components-0.0.5.dist-info/METADATA
plct_sphinx_components-0.0.5.dist-info/WHEEL
plct_sphinx_components-0.0.5.dist-info/RECORD
